{
  "entities": [
    {
      "name": "Указ",
      "description": "113 указ"
    },
    {
      "name": "Президент Российской Федерации",
      "description": "осуществляет руководство деятельностью федеральных органов исполнительной власти"
    },
    {
      "name": "Правительство Российской Федерации",
      "description": "представляет интересы в иных федеральных органах исполнительной власти"
    },
    {
      "name": "федеральные органы исполнительной власти",
      "description": "органы, в которых присваиваются классные чины по представлению руководителей этих органов или иных лиц, определённых Президентом Российской Федерации"
    },
    {
      "name": "иные федеральные государственные органы",
      "description": "органы, в которых классные чины присваиваются по представлению руководителей этих органов"
    },
    {
      "name": "аппараты федеральных государственных органов",
      "description": "места, где классные чины присваиваются по представлению руководителей этих органов"
    },
    {
      "name": "органы публичной власти федеральной территории 'Сириус'",
      "description": "органы, в которых классные чины присваиваются по представлению руководителей этих органов"
    }
  ],
  "relationships": [
    {
      "source": "Президент Российской Федерации",
      "relation": "осуществляет руководство",
      "target": "федеральные органы исполнительной власти"
    },
    {
      "source": "Правительство Российской Федерации",
      "relation": "представляет интересы",
      "target": "иные федеральные органы исполнительной власти"
    },
    {
      "source": "руководители федеральных органов исполнительной власти",
      "relation": "представляют для присвоения",
      "target": "классные чины"
    },
    {
      "source": "руководители иных федеральных государственных органов",
      "relation": "представляют для присвоения",
      "target": "классные чины"
    },
    {
      "source": "руководители аппаратов федеральных государственных органов",
      "relation": "представляют для присвоения",
      "target": "классные чины"
    },
    {
      "source": "руководители органов публичной власти федеральной территории 'Сириус'",
      "relation": "представляют для присвоения",
      "target": "классные чины"
    }
  ]
}