{
  "entities": [
    {
      "name": "Государственный советник Российской Федерации 2 класса",
      "description": "должность"
    },
    {
      "name": "подполковник",
      "description": "воинское звание"
    },
    {
      "name": "капитан 2 ранга",
      "description": "воинское звание"
    },
    {
      "name": "полиция (милиция)",
      "description": "ведомство"
    },
    {
      "name": "внутренняя служба",
      "description": "ведомство"
    },
    {
      "name": "юстиция",
      "description": "ведомство"
    },
    {
      "name": "таможенная служба",
      "description": "ведомство"
    },
    {
      "name": "государственный советник юстиции Российской Федерации 2 класса",
      "description": "должность в ведомстве юстиции"
    },
    {
      "name": "советник юстиции",
      "description": "должность в ведомстве юстиции"
    }
  ],
  "relationships": [
    {
      "source": "подполковник",
      "relation": "относится к воинскому званию",
      "target": "полиция (милиция), внутренняя служба, юстиция, таможенная служба"
    },
    {
      "source": "Государственный советник Российской Федерации 2 класса",
      "relation": "аналогичная должность в ведомствах",
      "target": "государственный советник юстиции Российской Федерации 2 класса"
    }
  ]
}