{
  "entities": [
    {
      "name": "Указ Президента РФ",
      "description": "от 31 декабря 2005 г. N 1574 'О Реестре должностей федеральной государственной'"
    },
    {
      "name": "Собрание законодательства Российской Федерации",
      "description": "официальный источник публикации законодательных актов"
    },
    {
      "name": "Указ Президента РФ от 2002 г. N 1129",
      "description": "О приведении актов Президента РСФСР и Президента Российской Федерации в соответствие с Трудовым кодексом Российской Федерации"
    }
  ],
  "relationships": [
    {
      "source": "Указ Президента РФ от 31 декабря 2005 г. N 1574",
      "relation": "относится к",
      "target": "Реестр должностей федеральной государственной"
    },
    {
      "source": "Указ Президента РФ от 2002 г. N 1129",
      "relation": "приводит в соответствие с",
      "target": "Трудовой кодекс Российской Федерации"
    }
  ]
}