{
  "entities": [
    {
      "name": "Указ Президента Российской Федерации",
      "description": "Нормативный акт, утверждающий Реестр должностей федеральной государственной гражданской службы."
    },
    {
      "name": "Президент Российской Федерации",
      "description": "Глава государства, издавший указ."
    },
    {
      "name": "В. Путин",
      "description": "Имя главы государства."
    },
    {
      "name": "Москва, Кремль",
      "description": "Место издания указа."
    },
    {
      "name": "N 1574",
      "description": "Номер указа Президента Российской Федерации от 31 декабря 2005 года."
    },
    {
      "name": "Реестр должностей федеральной государственной гражданской службы",
      "description": "Документ, утверждающий перечень должностей федеральной государственной гражданской службы."
    },
    {
      "name": "Указ Президента России от 26 февраля 2026 г. № 121",
      "description": "Нормативный акт, внёсший изменения в реестр."
    }
  ],
  "relationships": [
    {
      "source": "Президент Российской Федерации",
      "relation": "издал",
      "target": "Указ Президента Российской Федерации N 1574"
    },
    {
      "source": "Указ Президента Российской Федерации N 1574",
      "relation": "утвердил",
      "target": "Реестр должностей федеральной государственной гражданской службы"
    },
    {
      "source": "Указ Президента России от 26 февраля 2026 г. № 121",
      "relation": "внёс изменения",
      "target": "Реестр должностей федеральной государственной гражданской службы"
    }
  ]
}