{
  "entities": [
    {
      "name": "Указ Президента РФ",
      "description": "Нормативный акт, учреждающий должности федеральной государственной службы."
    },
    {
      "name": "Президент Российской Федерации",
      "description": "Глава государства, который осуществляет руководство некоторыми федеральными службами."
    },
    {
      "name": "Правительство Российской Федерации",
      "description": "Высший исполнительный орган государственной власти, который осуществляет руководство некоторыми федеральными службами."
    },
    {
      "name": "Федеральная служба",
      "description": "Орган исполнительной власти федерального уровня."
    },
    {
      "name": "Военнослужащий по контракту",
      "description": "Лицо, проходящее военную службу на контрактной основе."
    },
    {
      "name": "Сотрудник со специальным званием",
      "description": "Лицо, имеющее специальное звание и замещающее должность в федеральной службе."
    },
    {
      "name": "Федеральная государственная гражданская служба",
      "description": "Вид государственной службы, осуществляемой гражданскими лицами."
    }
  ],
  "relationships": [
    {
      "source": "Указ Президента РФ",
      "relation": "предусматривает",
      "target": "должности федеральной государственной службы"
    },
    {
      "source": "Президент Российской Федерации",
      "relation": "осуществляет руководство",
      "target": "федеральными службами"
    },
    {
      "source": "Правительство Российской Федерации",
      "relation": "осуществляет руководство",
      "target": "федеральными службами"
    },
    {
      "source": "Военнослужащий по контракту",
      "relation": "замещает",
      "target": "должность федеральной службы"
    },
    {
      "source": "Сотрудник со специальным званием",
      "relation": "замещает",
      "target": "должность федеральной службы"
    },
    {
      "source": "Федеральная служба",
      "relation": "включает",
      "target": "должности федеральной государственной гражданской службы"
    }
  ]
}