{
  "entities": [
    {
      "name": "Федеральная служба по вопросам государственной службы и кадров",
      "description": "структурное подразделение"
    },
    {
      "name": "Федеральная служба по осуществлению внутреннего финансового аудита",
      "description": "структурное подразделение"
    },
    {
      "name": "Федеральная служба по защите государственной тайны",
      "description": "структурное подразделение"
    },
    {
      "name": "Федеральная служба по организации мероприятий по мобилизационной подготовке и мобилизации",
      "description": "структурное подразделение"
    },
    {
      "name": "Президент Российской Федерации",
      "description": "осуществляет руководство деятельностью центрального аппарата федерального министерства"
    },
    {
      "name": "Военнослужащий",
      "description": "проходящий военную службу по контракту"
    },
    {
      "name": "Сотрудник",
      "description": "имеющий специальное звание"
    },
    {
      "name": "Гражданское лицо",
      "description": "замещающее должность федеральной государственной гражданской службы"
    },
    {
      "name": "Начальник департамента",
      "description": "наименование должности"
    },
    {
      "name": "Начальник управления",
      "description": "наименование должности"
    },
    {
      "name": "Начальник инспекции",
      "description": "наименование должности"
    },
    {
      "name": "Начальник отделения",
      "description": "наименование должности"
    },
    {
      "name": "Начальник отдела",
      "description": "наименование должности"
    }
  ],
  "relationships": [
    {
      "source": "Федеральная служба по вопросам государственной службы и кадров",
      "relation": "учреждена должность",
      "target": "начальник департамента"
    },
    {
      "source": "Федеральная служба по осуществлению внутреннего финансового аудита",
      "relation": "учреждена должность",
      "target": "начальник управления"
    },
    {
      "source": "Федеральная служба по защите государственной тайны",
      "relation": "учреждена должность",
      "target": "начальник инспекции"
    },
    {
      "source": "Федеральная служба по организации мероприятий по мобилизационной подготовке и мобилизации",
      "relation": "учреждена должность",
      "target": "начальник отделения"
    },
    {
      "source": "Центральное аппарат федерального министерства",
      "relation": "руководит деятельностью",
      "target": "Президент Российской Федерации"
    },
    {
      "source": "Военнослужащий или сотрудник",
      "relation": "замещает должность",
      "target": "должность федеральной государственной гражданской службы"
    }
  ]
}