{
  "entities": [
    {
      "name": "58-FZ_markdown",
      "description": ""
    },
    {
      "name": "Федеральный закон",
      "description": "от 14.02.2024 № 10-ФЗ"
    },
    {
      "name": "государственный служащий",
      "description": ""
    },
    {
      "name": "государственная служба",
      "description": ""
    }
  ],
  "relationships": [
    {
      "source": "Федеральный закон от 14.02.2024 № 10-ФЗ",
      "relation": "утратил силу",
      "target": "58-FZ_markdown"
    },
    {
      "source": "государственный служащий",
      "relation": "не вышел на",
      "target": "государственную службу"
    }
  ]
}