{
  "entities": [
    {
      "name": "58-FZ_markdown",
      "description": "Источник информации"
    },
    {
      "name": "государственная служба",
      "description": "Сфера деятельности, к которой относятся квалификационные требования"
    },
    {
      "name": "квалификационные требования",
      "description": "Требования к гражданам для замещения должностей государственной службы"
    }
  ],
  "relationships": [
    {
      "source": "58-FZ_markdown",
      "relation": "содержит информацию о",
      "target": "квалификационные требования"
    },
    {
      "source": "квалификационные требования",
      "relation": "относятся к",
      "target": "государственная служба"
    }
  ]
}