{
  "entities": [
    {
      "name": "аттестационная комиссия",
      "description": "орган, проводящий аттестацию гражданских служащих"
    },
    {
      "name": "гражданский служащий",
      "description": "лицо, проходящее аттестацию в рамках работы в государственных органах"
    },
    {
      "name": "аттестация",
      "description": "процесс оценки профессиональных качеств и компетенций гражданского служащего"
    }
  ],
  "relationships": [
    {
      "source": "гражданский служащий",
      "relation": "является членом",
      "target": "аттестационная комиссия"
    },
    {
      "source": "гражданский служащий",
      "relation": "проходит аттестацию",
      "target": "в рамках работы в государственных органах"
    }
  ]
}