{
  "entities": [
    {
      "name": "служебный контракт",
      "description": "соглашение между гражданским служащим и государственным органом о прохождении государственной гражданской службы"
    },
    {
      "name": "гражданский служащий",
      "description": "лицо, проходящее государственную гражданскую службу"
    },
    {
      "name": "государственный орган",
      "description": "организация, созданная для осуществления функций государства"
    }
  ],
  "relationships": [
    {
      "source": "служебный контракт",
      "relation": "предусматривает основания прекращения",
      "target": "гражданский служащий"
    },
    {
      "source": "гражданский служащий",
      "relation": "может отказаться от перевода",
      "target": "на иную должность гражданской службы"
    },
    {
      "source": "государственный орган",
      "relation": "может потребовать перевод",
      "target": "гражданского служащего"
    }
  ]
}