{
  "entities": [
    {
      "name": "Федеральный закон",
      "description": "от 30.12.2021 № 437-ФЗ"
    },
    {
      "name": "Гражданские служащие",
      "description": "субъекта Российской Федерации"
    },
    {
      "name": "Фонд оплаты труда",
      "description": "гражданских служащих субъекта Российской Федерации"
    }
  ],
  "relationships": [
    {
      "source": "Федеральный закон от 30.12.2021 № 437-ФЗ",
      "relation": "вносит изменения в",
      "target": "Порядок формирования фондов оплаты труда гражданских служащих субъекта Российской Федерации"
    },
    {
      "source": "Гражданские служащие",
      "relation": "подпадают под регулирование",
      "target": "Порядка формирования фондов оплаты труда"
    }
  ]
}