{
  "entities": [
    {
      "name": "79-FZ_markdown",
      "description": "источник документа"
    },
    {
      "name": "увольнение",
      "description": "процесс прекращения трудовых отношений"
    },
    {
      "name": "сокращение должностей гражданской службы",
      "description": "причина увольнения"
    },
    {
      "name": "упразднение гос",
      "description": "причина увольнения"
    }
  ],
  "relationships": [
    {
      "source": "79-FZ_markdown",
      "relation": "содержит информацию о",
      "target": "предстоящем увольнении в связи с сокращением должностей гражданской службы или упразднением гос"
    },
    {
      "source": "увольнение",
      "relation": "связано с",
      "target": "сокращение должностей гражданской службы"
    },
    {
      "source": "увольнение",
      "relation": "связано с",
      "target": "упразднение гос"
    }
  ]
}