{
  "entities": [
    {
      "name": "79-FZ_markdown",
      "description": "источник"
    },
    {
      "name": "Федеральный закон",
      "description": "законодательный акт"
    },
    {
      "name": "№ 116-ФЗ",
      "description": "номер закона"
    },
    {
      "name": "30.04.2021",
      "description": "дата"
    },
    {
      "name": "служебный контракт",
      "description": "тип документа"
    },
    {
      "name": "гражданский служащий",
      "description": "субъект права"
    },
    {
      "name": "замещаемая должность",
      "description": "объект замещения"
    }
  ],
  "relationships": [
    {
      "source": "79-FZ_markdown",
      "relation": "содержит информацию о",
      "target": "служебный контракт"
    },
    {
      "source": "Федеральный закон",
      "relation": "изменён",
      "target": "№ 116-ФЗ"
    },
    {
      "source": "30.04.2021",
      "relation": "дата принятия",
      "target": "№ 116-ФЗ"
    },
    {
      "source": "служебный контракт",
      "relation": "подлежит расторжению",
      "target": "гражданский служащий"
    },
    {
      "source": "гражданский служащий",
      "relation": "освобождается от",
      "target": "замещаемая должность"
    }
  ]
}