{
  "entities": [
    {
      "name": "антикоррупционное законодательство",
      "description": "законодательные нормы для борьбы с коррупцией"
    },
    {
      "name": "иные доходы",
      "description": "доходы, которые не указываются в строке 'Иные доходы'"
    },
    {
      "name": "родительская плата",
      "description": "плата за посещение дошкольного образовательного учреждения"
    },
    {
      "name": "нотариальная доверенность",
      "description": "доверенность, оформленная у нотариуса"
    },
    {
      "name": "почтовые расходы",
      "description": "расходы на отправку корреспонденции по почте"
    },
    {
      "name": "услуги представителя",
      "description": "юридические услуги представителя, оплачиваемые клиентом"
    }
  ],
  "relationships": [
    {
      "source": "антикоррупционное законодательство",
      "relation": "регулирует",
      "target": "указание доходов в строке 'Иные доходы'"
    },
    {
      "source": "родительская плата",
      "relation": "не указывается",
      "target": "в строке 'Иные доходы'"
    },
    {
      "source": "нотариальная доверенность",
      "relation": "связана с",
      "target": "оформлением документов"
    },
    {
      "source": "почтовые расходы",
      "relation": "возмещаются",
      "target": "по решению суда"
    },
    {
      "source": "услуги представителя",
      "relation": "возмещаются",
      "target": "по решению суда"
    }
  ]
}