{
  "entities": [
    {
      "name": "Указ Президента Российской Федерации",
      "description": "от 22 декабря 1999 г. № 1683 'Об утверждении перечней государственных'"
    },
    {
      "name": "Президент Российской Федерации",
      "description": "выпустил указ от 22 декабря 1999 г. № 1683"
    },
    {
      "name": "государственные перечни",
      "description": "утверждены указом Президента РФ от 22 декабря 1999 г. № 1683"
    }
  ],
  "relationships": [
    {
      "source": "Президент Российской Федерации",
      "relation": "выпустил",
      "target": "Указ Президента Российской Федерации"
    },
    {
      "source": "Указ Президента Российской Федерации",
      "relation": "утвердил",
      "target": "государственные перечни"
    }
  ]
}