{
  "entities": [
    {
      "name": "Специалист 3 разряда",
      "description": "9287"
    },
    {
      "name": "Секретарь судебного заседания",
      "description": "17 322"
    },
    {
      "name": "Главный специалист",
      "description": "16 706"
    },
    {
      "name": "Ведущий специалист",
      "description": "15 472"
    },
    {
      "name": "Специалист",
      "description": "14 228"
    },
    {
      "name": "Старший специалист 1 разряда",
      "description": "14 228"
    },
    {
      "name": "Старший специалист 2 разряда",
      "description": "13 612"
    },
    {
      "name": "Старший специалист 3 разряда",
      "description": "13 003"
    },
    {
      "name": "Специалист 1 разряда",
      "description": "11 759"
    },
    {
      "name": "Специалист 2 разряда",
      "description": "10 527"
    },
    {
      "name": "Руководитель аппарата - администратор суда",
      "description": "25 975"
    },
    {
      "name": "Начальник отдела",
      "description": "21 650"
    }
  ],
  "relationships": [
    {
      "source": "Специалист 3 разряда",
      "relation": "оклад",
      "target": "9287"
    },
    {
      "source": "Секретарь судебного заседания",
      "relation": "оклад",
      "target": "17 322"
    },
    {
      "source": "Главный специалист",
      "relation": "оклад",
      "target": "16 706"
    },
    {
      "source": "Ведущий специалист",
      "relation": "оклад",
      "target": "15 472"
    },
    {
      "source": "Специалист",
      "relation": "оклад",
      "target": "14 228"
    },
    {
      "source": "Старший специалист 1 разряда",
      "relation": "оклад",
      "target": "14 228"
    },
    {
      "source": "Старший специалист 2 разряда",
      "relation": "оклад",
      "target": "13 612"
    },
    {
      "source": "Старший специалист 3 разряда",
      "relation": "оклад",
      "target": "13 003"
    },
    {
      "source": "Специалист 1 разряда",
      "relation": "оклад",
      "target": "11 759"
    },
    {
      "source": "Специалист 2 разряда",
      "relation": "оклад",
      "target": "10 527"
    },
    {
      "source": "Руководитель аппарата - администратор суда",
      "relation": "оклад",
      "target": "25 975"
    },
    {
      "source": "Начальник отдела",
      "relation": "оклад",
      "target": "21 650"
    }
  ]
}