{
  "entities": [
    {
      "name": "Указ Президента Российской Федерации",
      "description": "документ, регулирующий денежное содержание федеральных государственных гражданских служащих аппарата Конституционного Суда Российской Федерации"
    },
    {
      "name": "Конституционный Суд Российской Федерации",
      "description": "государственный орган, для сотрудников которого установлены должностные оклады и ежемесячное денежное поощрение"
    },
    {
      "name": "Руководитель аппарата Конституционного Суда Российской Федерации",
      "description": "должность сотрудника с указанием должностного оклада и коэффициента"
    },
    {
      "name": "Заместитель руководителя аппарата Конституционного Суда Российской Федерации",
      "description": "должность сотрудника с указанием должностного оклада и коэффициента"
    },
    {
      "name": "Руководитель Секретариата Конституционного Суда Российской Федерации",
      "description": "должность сотрудника с указанием должностного оклада и коэффициента"
    },
    {
      "name": "Заместитель руководителя Секретариата Конституционного Суда Российской Федерации",
      "description": "должность сотрудника с указанием должностного оклада и коэффициента"
    },
    {
      "name": "Руководитель Секретариата Председателя Конституционного Суда Российской Федерации",
      "description": "должность сотрудника с указанием должностного оклада"
    },
    {
      "name": "Руководитель представительства Конституционного Суда Российской Федерации",
      "description": "должность сотрудника с указанием должностного оклада"
    }
  ],
  "relationships": [
    {
      "source": "Указ Президента Российской Федерации от 31.12.2021 № 749",
      "relation": "редактирует",
      "target": "Раздел 13. Должностные оклады и ежемесячное денежное поощрение федеральных государственных гражданских служащих аппарата Конституционного Суда Российской Федерации"
    },
    {
      "source": "Руководитель аппарата Конституционного Суда Российской Федерации",
      "relation": "получает оклад",
      "target": "32 403"
    },
    {
      "source": "Заместитель руководителя аппарата Конституционного Суда Российской Федерации",
      "relation": "получает оклад",
      "target": "31 278"
    },
    {
      "source": "Руководитель Секретариата Конституционного Суда Российской Федерации",
      "relation": "получает оклад",
      "target": "32 403"
    },
    {
      "source": "Заместитель руководителя Секретариата Конституционного Суда Российской Федерации",
      "relation": "получает оклад",
      "target": "31 278"
    },
    {
      "source": "Руководитель Секретариата Председателя Конституционного Суда Российской Федерации",
      "relation": "получает оклад",
      "target": "29 874"
    },
    {
      "source": "Руководитель представительства Конституционного Суда Российской Федерации",
      "relation": "получает оклад",
      "target": "29 874"
    }
  ]
}