{
  "entities": [
    {
      "name": "Специалист-эксперт",
      "description": "14 228"
    },
    {
      "name": "Старший специалист 1 разряда",
      "description": "14 228"
    },
    {
      "name": "Старший специалист 2 разряда",
      "description": "13 612"
    },
    {
      "name": "Старший специалист 3 разряда",
      "description": "13 003"
    },
    {
      "name": "Специалист 1 разряда",
      "description": "11 759"
    },
    {
      "name": "Специалист 2 разряда",
      "description": "10 527"
    },
    {
      "name": "Специалист 3 разряда",
      "description": "9287"
    },
    {
      "name": "Указ Президента Российской Федерации",
      "description": "от 08.07.2024 № 583"
    }
  ],
  "relationships": [
    {
      "source": "Специалист-эксперт",
      "relation": "оклад",
      "target": "14 228"
    },
    {
      "source": "Старший специалист 1 разряда",
      "relation": "оклад",
      "target": "14 228"
    },
    {
      "source": "Старший специалист 2 разряда",
      "relation": "оклад",
      "target": "13 612"
    },
    {
      "source": "Старший специалист 3 разряда",
      "relation": "оклад",
      "target": "13 003"
    },
    {
      "source": "Специалист 1 разряда",
      "relation": "оклад",
      "target": "11 759"
    },
    {
      "source": "Специалист 2 разряда",
      "relation": "оклад",
      "target": "10 527"
    },
    {
      "source": "Специалист 3 разряда",
      "relation": "оклад",
      "target": "9287"
    },
    {
      "source": "Указ Президента Российской Федерации от 08.07.2024 № 583",
      "relation": "редакция",
      "target": "должностные оклады"
    }
  ]
}