{
  "entities": [
    {
      "name": "Следственный комитет Российской Федерации",
      "description": "федеральный орган государственной власти"
    },
    {
      "name": "главные следственные управления",
      "description": "подразделения Следственного комитета РФ"
    },
    {
      "name": "следственные управления по субъектам Российской Федерации",
      "description": "подразделения Следственного комитета РФ в регионах"
    },
    {
      "name": "специализированные следственные управления и следственные отделы",
      "description": "специальные подразделения Следственного комитета РФ"
    },
    {
      "name": "военные следственные управления по военным округам, флотам",
      "description": "военные подразделения Следственного комитета РФ"
    },
    {
      "name": "межрайонные следственные отделы",
      "description": "подразделения Следственного комитета РФ на уровне межрайонных образований"
    },
    {
      "name": "следственные отделы по районам, городам, округам и районам в городах",
      "description": "местные подразделения Следственного комитета РФ"
    }
  ],
  "relationships": [
    {
      "source": "Следственный комитет Российской Федерации",
      "relation": "включает",
      "target": "главные следственные управления"
    },
    {
      "source": "Следственный комитет Российской Федерации",
      "relation": "включает",
      "target": "следственные управления по субъектам Российской Федерации"
    },
    {
      "source": "Следственный комитет Российской Федерации",
      "relation": "включает",
      "target": "специализированные следственные управления и следственные отделы"
    },
    {
      "source": "Следственный комитет Российской Федерации",
      "relation": "включает",
      "target": "военные следственные управления по военным округам, флотам"
    },
    {
      "source": "Следственный комитет Российской Федерации",
      "relation": "включает",
      "target": "межрайонные следственные отделы"
    },
    {
      "source": "Следственный комитет Российской Федерации",
      "relation": "включает",
      "target": "следственные отделы по районам, городам, округам и районам в городах"
    }
  ]
}