{
  "entities": [
    {
      "name": "кадровый резерв",
      "description": "список граждан и гражданских служащих, претендующих на замещение вакантных должностей федеральной гражданской службы"
    },
    {
      "name": "граждане",
      "description": "претендующие на замещение вакантной должности федеральной гражданской службы"
    },
    {
      "name": "гражданские служащие",
      "description": "претендующие на замещение вакантной должности федеральной гражданской службы в порядке должностного роста или увольняемые с федеральной гражданской службы"
    },
    {
      "name": "вакантная должность федеральной гражданской службы",
      "description": "должность, на которую претендуют граждане и гражданские служащие"
    },
    {
      "name": "конкурс",
      "description": "процедура отбора кандидатов для включения в кадровый резерв или замещения вакантной должности"
    },
    {
      "name": "аттестация",
      "description": "процесс оценки соответствия гражданских служащих занимаемой должности"
    }
  ],
  "relationships": [
    {
      "source": "граждане",
      "relation": "включаются в",
      "target": "кадровый резерв"
    },
    {
      "source": "гражданские служащие",
      "relation": "включаются в",
      "target": "кадровый резерв"
    },
    {
      "source": "гражданские служащие",
      "relation": "претендуют на замещение",
      "target": "вакантная должность федеральной гражданской службы"
    },
    {
      "source": "граждане",
      "relation": "подлежат отбору через",
      "target": "конкурс"
    },
    {
      "source": "гражданские служащие",
      "relation": "подлежат отбору через",
      "target": "конкурс"
    },
    {
      "source": "гражданские служащие",
      "relation": "проходят оценку через",
      "target": "аттестацию"
    }
  ]
}