{
  "entities": [
    {
      "name": "№ 112 приказ",
      "description": "источник информации"
    },
    {
      "name": "претендент на замещение вакантной должности гражданской службы",
      "description": "участник процесса найма"
    },
    {
      "name": "вакантная должность гражданской службы",
      "description": "объект поиска кандидата"
    }
  ],
  "relationships": [
    {
      "source": "№ 112 приказ",
      "relation": "упоминается в контексте",
      "target": "претендент на замещение вакантной должности гражданской службы"
    },
    {
      "source": "претендент на замещение вакантной должности гражданской службы",
      "relation": "не допущен к участию",
      "target": "конкур"
    }
  ]
}